hpc_runner/__init__.py
hpc_runner/_version.py
hpc_runner/py.typed
hpc_runner/cli/__init__.py
hpc_runner/cli/cancel.py
hpc_runner/cli/config.py
hpc_runner/cli/main.py
hpc_runner/cli/monitor.py
hpc_runner/cli/run.py
hpc_runner/cli/status.py
hpc_runner/core/__init__.py
hpc_runner/core/config.py
hpc_runner/core/descriptors.py
hpc_runner/core/exceptions.py
hpc_runner/core/job.py
hpc_runner/core/job_array.py
hpc_runner/core/job_info.py
hpc_runner/core/resources.py
hpc_runner/core/result.py
hpc_runner/core/types.py
hpc_runner/schedulers/__init__.py
hpc_runner/schedulers/base.py
hpc_runner/schedulers/detection.py
hpc_runner/schedulers/local/__init__.py
hpc_runner/schedulers/local/scheduler.py
hpc_runner/schedulers/local/templates/job.sh.j2
hpc_runner/schedulers/sge/__init__.py
hpc_runner/schedulers/sge/args.py
hpc_runner/schedulers/sge/parser.py
hpc_runner/schedulers/sge/scheduler.py
hpc_runner/schedulers/sge/templates/batch.sh.j2
hpc_runner/schedulers/sge/templates/interactive.sh.j2
hpc_runner/templates/__init__.py
hpc_runner/templates/engine.py
hpc_runner/tui/__init__.py
hpc_runner/tui/app.py
hpc_runner/tui/snapshot.py
hpc_runner/tui/components/__init__.py
hpc_runner/tui/components/detail_panel.py
hpc_runner/tui/components/filter_bar.py
hpc_runner/tui/components/filter_popup.py
hpc_runner/tui/components/job_table.py
hpc_runner/tui/providers/__init__.py
hpc_runner/tui/providers/jobs.py
hpc_runner/tui/screens/__init__.py
hpc_runner/tui/screens/confirm.py
hpc_runner/tui/screens/job_details.py
hpc_runner/tui/screens/log_viewer.py
hpc_runner/tui/styles/monitor.tcss
hpc_runner/workflow/__init__.py
hpc_runner/workflow/dependency.py
hpc_runner/workflow/pipeline.py
hpc_runner-0.2.1.dist-info/METADATA
hpc_runner-0.2.1.dist-info/WHEEL
hpc_runner-0.2.1.dist-info/entry_points.txt
hpc_runner-0.2.1.dist-info/RECORD
